scenaripy_api.py
scenaripy_api-6.4.4.dist-info/licenses/LICENSE
scenaripy_api-6.4.4.dist-info/WHEEL
scenaripy_api-6.4.4.dist-info/METADATA
scenaripy_api-6.4.4.dist-info/RECORD
